LICENSE
MANIFEST.in
README.txt
setup.cfg
setup.py
doc/Makefile
doc/ROADMAP.txt
doc/SCHEMA-PREAMBLE.txt
doc/__init__.py
doc/build/doctrees/environment.pickle
doc/build/doctrees/index.doctree
doc/build/doctrees/design/index.doctree
doc/build/doctrees/design/principles.doctree
doc/build/doctrees/design/structures.doctree
doc/build/doctrees/install/index.doctree
doc/build/doctrees/install/linux.doctree
doc/build/doctrees/install/macosx.doctree
doc/build/doctrees/install/windows.doctree
doc/build/doctrees/reference/command-line.doctree
doc/build/doctrees/reference/database-tour.doctree
doc/build/doctrees/reference/database-usage.doctree
doc/build/doctrees/reference/glossary.doctree
doc/build/doctrees/reference/index.doctree
doc/build/doctrees/reference/namespaces.doctree
doc/build/doctrees/reference/schema-definition.doctree
doc/build/doctrees/reference/t_namespaces.doctree
doc/build/doctrees/reference/transaction-hook-methods.doctree
doc/build/doctrees/tutorial/index.doctree
doc/build/doctrees/tutorial/moviereviews/index.doctree
doc/build/doctrees/tutorial/moviereviews/part1.doctree
doc/build/doctrees/tutorial/moviereviews/part2.doctree
doc/build/html/.buildinfo
doc/build/html/genindex.html
doc/build/html/index.html
doc/build/html/objects.inv
doc/build/html/search.html
doc/build/html/searchindex.js
doc/build/html/_sources/index.txt
doc/build/html/_sources/design/index.txt
doc/build/html/_sources/design/principles.txt
doc/build/html/_sources/design/structures.txt
doc/build/html/_sources/install/index.txt
doc/build/html/_sources/install/linux.txt
doc/build/html/_sources/install/macosx.txt
doc/build/html/_sources/install/windows.txt
doc/build/html/_sources/reference/command-line.txt
doc/build/html/_sources/reference/database-tour.txt
doc/build/html/_sources/reference/database-usage.txt
doc/build/html/_sources/reference/glossary.txt
doc/build/html/_sources/reference/index.txt
doc/build/html/_sources/reference/namespaces.txt
lib/libschevo.egg-info/PKG-INFO
lib/libschevo.egg-info/SOURCES.txt
lib/libschevo.egg-info/dependency_links.txt
lib/libschevo.egg-info/entry_points.txt
lib/libschevo.egg-info/not-zip-safe
lib/libschevo.egg-info/requires.txt
lib/libschevo.egg-info/top_level.txt
