Metadata-Version: 1.2
Name: libschevo
Version: 4.1
Summary: Next-generation Object-Oriented DBMS
Home-page: https://www.isotopesoftware.ca/software/libschevo/
Maintainer: Etienne Robillard
Maintainer-email: admin@isotopesoftware.ca
License: Apache 2.0 License
Keywords: database dbms schevo libschevo
Platform: UNKNOWN
Classifier: Development Status :: 4 - Beta
Classifier: Environment :: Console
Classifier: Intended Audience :: Developers
Classifier: License :: OSI Approved :: MIT License
Classifier: Operating System :: OS Independent
Classifier: Programming Language :: Python
Classifier: Topic :: Database :: Database Engines/Servers
Classifier: Topic :: Software Development :: Libraries :: Application Frameworks
